LITALib/__init__.py
LITALib/data/__init__.py
LITALib/data/crash.py
LITALib/data/lt.py
LITALib/data/rci.py
LITALib/diagnosis/__init__.py
LITALib/diagnosis/clustering.py
LITALib/diagnosis/clustering_2.py
LITALib/diagnosis/core.py
LITALib/diagnosis/diagnosis.py
LITALib/diagnosis/sliding.py
LITALib/diagnosis/statistics.py
LITALib/rci/__init__.py
LITALib/rci/aggregation.py
LITALib/rci/collection.py
LITALib/rci/segmentation.py
LITALib/rci/utilities.py
litalib-0.0.4.dist-info/LICENSE
litalib-0.0.4.dist-info/METADATA
litalib-0.0.4.dist-info/WHEEL
litalib-0.0.4.dist-info/top_level.txt
litalib-0.0.4.dist-info/RECORD
