Metadata-Version: 2.1
Name: litalib
Version: 0.0.4
Summary: A package of ALMS lighting data process
Home-page: https://its.cutr.usf.edu/alms/
Author: Zhenyu Wang
Author-email: wonstran@hotmail.com
License: MIT
Keywords: litalib
Classifier: Development Status :: 3 - Alpha
Classifier: Intended Audience :: End Users/Desktop
Classifier: License :: OSI Approved :: MIT License
Classifier: Programming Language :: Python :: 3
Requires-Python: >=3.7
License-File: LICENSE
Requires-Dist: numpy
Requires-Dist: pandas
Requires-Dist: matplotlib
Requires-Dist: geopandas
